helpmepack/__init__.py
helpmepack/helpmepack.py
helpmepack/all_templates/pyproject.toml
helpmepack/all_templates/setup.cfg
helpmepack/all_templates/licenses_templates/agpl3-header.txt
helpmepack/all_templates/licenses_templates/agpl3.txt
helpmepack/all_templates/licenses_templates/apache-header.txt
helpmepack/all_templates/licenses_templates/apache.txt
helpmepack/all_templates/licenses_templates/bsd2.txt
helpmepack/all_templates/licenses_templates/bsd3.txt
helpmepack/all_templates/licenses_templates/cc0-header.txt
helpmepack/all_templates/licenses_templates/cc0.txt
helpmepack/all_templates/licenses_templates/cc_by-header.txt
helpmepack/all_templates/licenses_templates/cc_by.txt
helpmepack/all_templates/licenses_templates/cc_by_nc-header.txt
helpmepack/all_templates/licenses_templates/cc_by_nc.txt
helpmepack/all_templates/licenses_templates/cc_by_nc_nd-header.txt
helpmepack/all_templates/licenses_templates/cc_by_nc_nd.txt
helpmepack/all_templates/licenses_templates/cc_by_nc_sa-header.txt
helpmepack/all_templates/licenses_templates/cc_by_nc_sa.txt
helpmepack/all_templates/licenses_templates/cc_by_nd-header.txt
helpmepack/all_templates/licenses_templates/cc_by_nd.txt
helpmepack/all_templates/licenses_templates/cc_by_sa-header.txt
helpmepack/all_templates/licenses_templates/cc_by_sa.txt
helpmepack/all_templates/licenses_templates/cddl.txt
helpmepack/all_templates/licenses_templates/epl.txt
helpmepack/all_templates/licenses_templates/gpl2.txt
helpmepack/all_templates/licenses_templates/gpl3-header.txt
helpmepack/all_templates/licenses_templates/gpl3.txt
helpmepack/all_templates/licenses_templates/isc.txt
helpmepack/all_templates/licenses_templates/lgpl.txt
helpmepack/all_templates/licenses_templates/mit.txt
helpmepack/all_templates/licenses_templates/mpl-header.txt
helpmepack/all_templates/licenses_templates/mpl.txt
helpmepack/all_templates/licenses_templates/unlicense.txt
helpmepack/all_templates/licenses_templates/wtfpl-header-warranty.txt
helpmepack-0.0.2.dist-info/LICENSE
helpmepack-0.0.2.dist-info/METADATA
helpmepack-0.0.2.dist-info/WHEEL
helpmepack-0.0.2.dist-info/top_level.txt
helpmepack-0.0.2.dist-info/RECORD
