Metadata-Version: 2.1
Name: helpmepack
Version: 0.0.2
Summary: Python Package helper CLI
Home-page: https://github.com/dviralfi/HelpMePack
Author: Dvir Alfi
Author-email: dviralafiprogram@gmail.com
Project-URL: Bug Tracker, https://github.com/pypa/sampleproject/issues
Classifier: Programming Language :: Python :: 3
Classifier: License :: OSI Approved :: MIT License
Classifier: Operating System :: OS Independent
Requires-Python: >=3.7
License-File: LICENSE
